{"body":[{"tokens":[{"dmoot":{"analyses":[{"details":"3020","tag":"3020","prob":0}],"tag":"3020"},"tokpp":["CARD"],"msafe":1,"moot":{"word":"3020","tag":"CARD","lemma":"3020"},"lts":[{"w":0,"hi":"dRainultsvainul"}],"toka":["CARD"],"f":3,"text":"3020","xlit":{"isLatin1":1,"latin1Text":"3020","isLatinExt":1}},{"dmoot":{"tag":"Hessischer","analyses":[{"details":"Hessischer","prob":0,"tag":"Hessischer"}]},"lang":["de"],"f":1,"moot":{"word":"Hessischer","tag":"ADJA","lemma":"hessisch"},"msafe":1,"lts":[{"w":0,"hi":"hesiSe6"}],"xlit":{"isLatinExt":1,"latin1Text":"Hessischer","isLatin1":1},"hasmorph":1,"text":"Hessischer"},{"dmoot":{"analyses":[{"details":"Landtag","prob":0,"tag":"Landtag"}],"tag":"Landtag"},"exlex":"Landtag","errid":"ec","lang":["de"],"moot":{"tag":"NN","lemma":"Landtag","word":"Landtag"},"lts":[{"w":0,"hi":"lantak"}],"msafe":1,"f":734,"xlit":{"isLatin1":1,"latin1Text":"Landtag","isLatinExt":1},"text":"Landtag","hasmorph":1},{"dmoot":{"analyses":[{"details":"·","tag":"·","prob":0}],"tag":"·"},"tokpp":["$("],"text":"·","xlit":{"latin1Text":"·","isLatin1":1,"isLatinExt":1},"lts":[{"hi":"","w":0}],"moot":{"word":"·","tag":"XY","lemma":"·"},"msafe":1,"toka":["$("],"lang":["xy"]},{"xlit":{"isLatinExt":1,"isLatin1":1,"latin1Text":"20."},"text":"20.","lts":[{"w":0,"hi":"tsvainul"}],"moot":{"word":"20.","tag":"ADJA","lemma":"20."},"msafe":1,"f":9780,"toka":["ADJA","$ORD"],"tokpp":["ADJA","$ORD"],"dmoot":{"analyses":[{"details":"20.","prob":0,"tag":"20."}],"tag":"20."},"exlex":"20.","errid":"ec"},{"xlit":{"isLatinExt":1,"isLatin1":1,"latin1Text":"Wahlperiode"},"text":"Wahlperiode","hasmorph":1,"lang":["de"],"lts":[{"w":0,"hi":"valpe6iode"}],"moot":{"lemma":"Wahlperiode","tag":"NN","word":"Wahlperiode"},"msafe":1,"f":5,"dmoot":{"analyses":[{"prob":0,"tag":"Wahlperiode","details":"Wahlperiode"}],"tag":"Wahlperiode"}},{"tokpp":["$("],"dmoot":{"tag":"·","analyses":[{"details":"·","tag":"·","prob":0}]},"lang":["xy"],"moot":{"tag":"XY","lemma":"·","word":"·"},"lts":[{"hi":"","w":0}],"msafe":1,"toka":["$("],"xlit":{"latin1Text":"·","isLatin1":1,"isLatinExt":1},"text":"·"},{"toka":["ADJA","$ORD"],"f":3315,"moot":{"word":"40.","lemma":"40.","tag":"ADJA"},"msafe":1,"lts":[{"hi":"fi6nul","w":0}],"text":"40.","xlit":{"isLatinExt":1,"latin1Text":"40.","isLatin1":1},"errid":"ec","dmoot":{"tag":"40.","analyses":[{"details":"40.","prob":0,"tag":"40."}]},"exlex":"40.","tokpp":["ADJA","$ORD"]},{"text":"Sitzung","hasmorph":1,"xlit":{"isLatin1":1,"latin1Text":"Sitzung","isLatinExt":1},"moot":{"tag":"NN","lemma":"Sitzung","word":"Sitzung"},"msafe":1,"lts":[{"hi":"zitsuN","w":0}],"f":741,"lang":["de"],"errid":"ec","exlex":"Sitzung","dmoot":{"analyses":[{"prob":0,"tag":"Sitzung","details":"Sitzung"}],"tag":"Sitzung"}},{"xlit":{"latin1Text":"·","isLatin1":1,"isLatinExt":1},"text":"·","lang":["xy"],"moot":{"word":"·","tag":"XY","lemma":"·"},"msafe":1,"lts":[{"hi":"","w":0}],"toka":["$("],"dmoot":{"tag":"·","analyses":[{"prob":0,"tag":"·","details":"·"}]},"tokpp":["$("]},{"lts":[{"w":0,"hi":"tsvaizeCs"}],"moot":{"lemma":"26.","tag":"ADJA","word":"26."},"msafe":1,"toka":["ADJA","$ORD"],"f":5793,"xlit":{"latin1Text":"26.","isLatin1":1,"isLatinExt":1},"text":"26.","exlex":"26.","dmoot":{"tag":"26.","analyses":[{"details":"26.","tag":"26.","prob":0}]},"tokpp":["ADJA","$ORD"],"errid":"ec"},{"lang":["de"],"lts":[{"hi":"mai","w":0}],"moot":{"word":"Mai","tag":"NN","lemma":"Mai"},"msafe":1,"mextra":[{"hi":"Mai[_NE][firstname][src=hlgl]++","w":0}],"xlit":{"isLatin1":1,"latin1Text":"Mai","isLatinExt":1},"hasmorph":1,"text":"Mai","dmoot":{"tag":"Mai","analyses":[{"details":"Mai","tag":"Mai","prob":0}]},"exlex":"Mai","mlatin":[{"hi":"[_FM][lat]","w":0}],"errid":"ec"},{"lts":[{"hi":"tsvainultsvainul","w":0}],"moot":{"word":"2020","lemma":"2020","tag":"CARD"},"msafe":1,"toka":["CARD"],"f":10,"xlit":{"latin1Text":"2020","isLatin1":1,"isLatinExt":1},"text":"2020","dmoot":{"analyses":[{"details":"2020","prob":0,"tag":"2020"}],"tag":"2020"},"tokpp":["CARD"]}],"lang":"de"}]}